piwigo/__init__.py
piwigo/ws.py
piwigo/__pycache__/WsErrorException.cpython-312.pyc
piwigo/__pycache__/WsNotExistException.cpython-312.pyc
piwigo/__pycache__/WsPiwigoException.cpython-312.pyc
piwigo/__pycache__/__init__.cpython-312.pyc
piwigo/__pycache__/exceptions.cpython-312.pyc
piwigo/__pycache__/piwigo.cpython-312.pyc
piwigo/__pycache__/ws.cpython-312.pyc
piwigo2-2.0.1.dist-info/AUTHORS.txt
piwigo2-2.0.1.dist-info/LICENSE
piwigo2-2.0.1.dist-info/METADATA
piwigo2-2.0.1.dist-info/WHEEL
piwigo2-2.0.1.dist-info/top_level.txt
piwigo2-2.0.1.dist-info/RECORD
