Metadata-Version: 2.1
Name: piwigo2
Version: 2.0.1
Summary: piwigo API wrapper
Home-page: https://github.com/DaanHolleman/piwigo.git
Author: FrÃ©dÃ©ric Aoustin,Daan Holleman
Author-email: fraoustin@gmail.com,dholleman123@gmail.com
Classifier: Programming Language :: Python
Classifier: License :: OSI Approved :: GNU General Public License v2 (GPLv2)
Classifier: Operating System :: OS Independent
Classifier: Programming Language :: Python :: 2.7
Classifier: Programming Language :: Python :: 3
Classifier: Programming Language :: Python :: 3.0
Classifier: Programming Language :: Python :: 3.1
Classifier: Programming Language :: Python :: 3.2
Classifier: Programming Language :: Python :: 3.3
Classifier: Programming Language :: Python :: 3.4
License-File: LICENSE
License-File: AUTHORS.txt
Requires-Dist: requests
